{
  "source_file": "каталог_координат_25834.pdf",
  "report_id": "25834",
  "processed_at": "2026-06-28T00:48:24",
  "ocr": {
    "pages": 4,
    "failed_pages": 0,
    "mean_confidence": 49.7,
    "needs_review": true
  },
  "coordinates": [
    {
      "id": "18",
      "name": "Алайтыр заладный",
      "valid": true,
      "lat_dms": "49°04'",
      "lon_dms": "74°21'",
      "lat_decimal": 49.066667,
      "lon_decimal": 74.35
    },
    {
      "id": "24",
      "name": "Алайгыр восточный",
      "valid": true,
      "lat_dms": "49°00'",
      "lon_dms": "95°54'",
      "lat_decimal": 49.0,
      "lon_decimal": 95.9
    },
    {
      "id": "26",
      "name": "Участок Актобе",
      "valid": true,
      "lat_dms": "48°56'",
      "lon_dms": "74°04'",
      "lat_decimal": 48.933333,
      "lon_decimal": 74.066667
    },
    {
      "id": "28",
      "name": "Узунагац",
      "valid": true,
      "lat_dms": "48°31'",
      "lon_dms": "74°21'",
      "lat_decimal": 48.516667,
      "lon_decimal": 74.35
    },
    {
      "id": "0",
      "name": "Участок Кварцевый",
      "valid": true,
      "lat_dms": "47°50'",
      "lon_dms": "71°46'",
      "lat_decimal": 47.833333,
      "lon_decimal": 71.766667
    }
  ],
  "entities": {
    "minerals": [
      "кварц"
    ],
    "grades_g_per_t": [],
    "coordinates_in_text": []
  },
  "raw_text": "!\n` 5% 54 #Т 6% *\n№ & 9Т ® иелеко;, <Т {\n| 65 & 55 4% 1 неложн; яоховь; ©Т\n20 $4 95 4% ®яв05 ЕВН2ОтО&бос 2Т\nі $5 5; 52 1% И опостнему ТТ\n? Т 24 п 6% о 0Т *\n55 24 67 % нКаКно/у 6\nё 90 % 15 & *\n00 %4 %5 4% ИМНят ослбехиу @ ;\n… 9Т 1/ 95 4% э *\n| 6Т %4 85 4% & **\n81 14 85 4% е й -- ›\n81 14 85 4% Т & \"#ло .\n1 ' вТ 14 85 4% билнеояу —\n: - ® 14 м (& : х '\n° (8&09я) 009 1/ 05 &* нвлеяоп-ете9 9\n* % 14 0 * ^ наяейио) < ’\n% 1Ё 0% 8% ‚° имнжобоЖийт +\n' %2 14 90 8% малепиоу-етея < *\n0г 1/ {0 % увоех г *\n| «9То1ё .5089 — иенеяд°п °Т @.\nМсти. «° йы — |\nноУниКа00х  |} «охоовь окееевц 98\n*116761-006Т ®е\n* И нохобнуелу Хлов20 Я ХВНИТбооя\n| ДОКУДУУ ‹‘\nпЛ рня ‘\n48 15 73 55\n48 59 75 07\n` 48 51 73 @5 _\n48 51 7% 07\n°@ 18 Алайтыр заладный 49 %5' 747 » |\n49 04 74 21 |\n49 0% 7 2% ;\n49 05 74 24 ;\n49 (т 74 19 У\n49 01 74 Г А\n19 Кокцатас 49 16 7% 16 -\nы 24 Алайгыр восточный 49 00 95 54 __\n48 37 74 50 |\n26 Участок Актобе 48 56 74 04 |\n1 27 Каратоганбай 48 55 74 10\n| 28 Узунагац 48 31 74 21 :\n| $0 Участок Кварцевый 47 50 71 46 ‹\n| 48 54 72 51\n‘ 52 Участок Доней-Кызыл 48 5 72 53 .і\n@м ооаь ° аб ноны\nон ов *\nй & от ® Ё _ _\n10 у — кито оепоойюнц & @.\nнЫ # —\n. ё п “ . К: й\n\\ * 16а этнузчати ’\nра\nд \\ Т - о\n' (*116/,-046Т В !\n@ еноией ололойнелу илоВЬ ионьо5о089-0Д0 & |\n; ототое ен хВлооВ@ хняомоИоН 0 Клоеьло Я) )\nё ‚дой ооы ТУНИТа00я ЛОТУЧМУЯ |\n° *у*а яечнеха у знворат :\n|  вип4еп вечохоион-олокоеМ келобнтел у | ®\n| випитеноме ввнэеьиен% Ё\n-оод-одокоол КеНонОКПИОМ Вехо нтелу —\n}| ЗИнЗЫВУ4ЦА ЗОМОЗЬИ10М03) ЗОНЗУУи401Ива3! зохануиохусуу-ончичалнзи @ —\nЁ а22 !АО)ЮХЧЁ\\!)! ИИЛОНОЗ: о9тОазаоиниУ Ё _"
}